todoforge/__init__.py
todoforge/commands/__init__.py
todoforge/commands/spaces.py
todoforge/main.py
todoforge/utils/__init__.py
todoforge/utils/config.py
todoforge/utils/constants.py
todoforge/utils/db.py
todoforge/utils/helper.py
todoforge/utils/models.py
todoforge/utils/ui/menu.py
todoforge-1.0.0.dist-info/METADATA
todoforge-1.0.0.dist-info/WHEEL
todoforge-1.0.0.dist-info/entry_points.txt
todoforge-1.0.0.dist-info/RECORD
