Metadata-Version: 2.1
Name: todoforge
Version: 1.0.0
Summary: 
Author: Hemanth
Author-email: hemanthhari2000@gmail.com
Requires-Python: >=3.12,<4.0
Classifier: Programming Language :: Python :: 3
Classifier: Programming Language :: Python :: 3.12
Classifier: Programming Language :: Python :: 3.13
Requires-Dist: black (>=24.10.0,<25.0.0)
Requires-Dist: mypy (>=1.13.0,<2.0.0)
Requires-Dist: pre-commit (>=4.0.1,<5.0.0)
Requires-Dist: pydantic (>=2.9.2,<3.0.0)
Requires-Dist: ruff (>=0.7.1,<0.8.0)
Requires-Dist: typer (>=0.12.5,<0.13.0)
